p3dimgui/__init__.py
p3dimgui/backend.py
p3dimgui/shaders.py
p3dimgui/utilities/ExplorerManager.py
p3dimgui/utilities/IntervalTimeSlider.py
p3dimgui/utilities/PlaceManager.py
p3dimgui/utilities/PlacePanel.py
p3dimgui/utilities/SceneGraphExplorer.py
p3dimgui/utilities/TimeSliderManager.py
panda3d_imgui-1.0.2.dist-info/METADATA
panda3d_imgui-1.0.2.dist-info/WHEEL
panda3d_imgui-1.0.2.dist-info/licenses/LICENSE
panda3d_imgui-1.0.2.dist-info/RECORD
