Metadata-Version: 2.4
Name: panda3d-imgui
Version: 1.0.2
Summary: A Dear ImGui backend for Python-based Panda3D projects with built-in utilities.
Project-URL: Homepage, https://github.com/LittleToonCat/panda3d-imgui
Project-URL: Issues, https://github.com/LittleToonCat/panda3d-imgui/issues
Author-email: Little Cat <toontownlittlecat@gmail.com>
License-Expression: MIT
License-File: LICENSE
Keywords: Dear ImGui,Panda3D,imgui-bundle
Classifier: Operating System :: OS Independent
Classifier: Programming Language :: Python :: 3
Requires-Python: >=3.10
Requires-Dist: imgui-bundle==1.92.4
Requires-Dist: panda3d
Requires-Dist: pyperclip
